setup.py
simtk/__init__.py
simtk.units.egg-info/PKG-INFO
simtk.units.egg-info/SOURCES.txt
simtk.units.egg-info/dependency_links.txt
simtk.units.egg-info/top_level.txt
simtk/unit/__init__.py
simtk/unit/basedimension.py
simtk/unit/baseunit.py
simtk/unit/constants.py
simtk/unit/doctests.py
simtk/unit/mymatrix.py
simtk/unit/prefix.py
simtk/unit/quantity.py
simtk/unit/standard_dimensions.py
simtk/unit/unit.py
simtk/unit/unit_definitions.py
simtk/unit/unit_math.py
simtk/unit/unit_operators.py