Metadata-Version: 1.0
Name: simtk.units
Version: 0.1
Summary: Units for python
Home-page: https://github.com/rmcgibbo/simtk.unit
Author: Christopher M. Bruns
Author-email: cmbruns@stanford.edu
License: Python Software Foundation License (BSD-like)
Platform: Linux
Platform: Mac OS X
Platform: Windows
